mcp_server_cloud_assistant/__init__.py
mcp_server_cloud_assistant/config.py
mcp_server_cloud_assistant/server.py
cloud_assistant_mcp_server-0.1.0.dist-info/METADATA
cloud_assistant_mcp_server-0.1.0.dist-info/WHEEL
cloud_assistant_mcp_server-0.1.0.dist-info/entry_points.txt
cloud_assistant_mcp_server-0.1.0.dist-info/top_level.txt
cloud_assistant_mcp_server-0.1.0.dist-info/RECORD
