Metadata-Version: 2.4
Name: cloud-assistant-mcp-server
Version: 0.1.0
Summary: Add your description here
Requires-Python: >=3.13
Requires-Dist: mcp[cli]>=1.6.0
Requires-Dist: volcengine-python-sdk>=1.1.5
